toydl/__init__.py
toydl/functional/__init__.py
toydl/nn/__init__.py
toydl/nn/activation.py
toydl/nn/convolution.py
toydl/nn/criterion.py
toydl/nn/flatten.py
toydl/nn/linear.py
toydl/nn/module.py
toydl/nn/sequential.py
toydl/optim/__init__.py
toydl/optim/adadelta.py
toydl/optim/adagrad.py
toydl/optim/adam.py
toydl/optim/baseoptimizer.py
toydl/optim/rmsprop.py
toydl/optim/sgd.py
toydl/utils/__init__.py
toydl/utils/data.py
toydl/utils/image.py
pytoydl-0.0.4.dist-info/LICENSE
pytoydl-0.0.4.dist-info/METADATA
pytoydl-0.0.4.dist-info/WHEEL
pytoydl-0.0.4.dist-info/top_level.txt
pytoydl-0.0.4.dist-info/zip-safe
pytoydl-0.0.4.dist-info/RECORD
