Metadata-Version: 2.1
Name: pytoydl
Version: 0.0.4
Summary: Pytoydl: A toy deep learning framework built upon numpy.
Home-page: https://github.com/CharlesPikachu/pytoydl
Author: Zhenchao Jin
Author-email: charlesblwx@gmail.com
License: Apache License 2.0
Platform: UNKNOWN
Classifier: License :: OSI Approved :: Apache Software License
Classifier: Programming Language :: Python :: 3
Classifier: Intended Audience :: Developers
Classifier: Operating System :: OS Independent
License-File: LICENSE
Requires-Dist: numpy
